datetag_pdf/__init__.py
datetag_pdf/cli.py
datetag_pdf-0.1.dist-info/LICENSE
datetag_pdf-0.1.dist-info/METADATA
datetag_pdf-0.1.dist-info/WHEEL
datetag_pdf-0.1.dist-info/entry_points.txt
datetag_pdf-0.1.dist-info/RECORD
